jellyfish-1.2.0.dist-info/METADATA
jellyfish-1.2.0.dist-info/WHEEL
jellyfish-1.2.0.dist-info/licenses/LICENSE
jellyfish/__init__.pyi
jellyfish/_jellyfish.py
jellyfish/__init__.py
jellyfish/py.typed
jellyfish/_rustyfish.cpython-312-darwin.so
jellyfish-1.2.0.dist-info/RECORD
