Metadata-Version: 2.4
Name: jellyfish
Version: 1.2.0
Classifier: Programming Language :: Rust
Classifier: Programming Language :: Python :: Implementation :: CPython
Classifier: Programming Language :: Python :: Implementation :: PyPy
Classifier: License :: OSI Approved :: MIT License
Classifier: Operating System :: OS Independent
Classifier: Development Status :: 5 - Production/Stable
Classifier: Intended Audience :: Developers
License-File: LICENSE
Summary: Approximate and phonetic matching of strings.
Author: James Turk <dev@jamesturk.net>
Author-email: James Turk <dev@jamesturk.net>
License: MIT
Requires-Python: >=3.9
Project-URL: homepage, https://jamesturk.github.io/jellyfish/
Project-URL: documentation, https://jamesturk.github.io/jellyfish/
Project-URL: repository, https://github.com/jamesturk/jellyfish/
